{
  "Title":      "OpenLDAP",
  "SourceUrl":  "ftp://ftp.openldap.org/pub/OpenLDAP/openldap-release/",
  "Tracker":    "https://abi-laboratory.pro/tracker/timeline/openldap/",
  "Maintainer": "Andrey P.",

  "Reports": [
  {
    "Version":           "2.4.44",
    "From":              "2.4.43",
    "BC":                "100%",
    "Added":             0,
    "Removed":           0,
    "TotalProblems":     0,
    "ObjectsAdded":      0,
    "ObjectsRemoved":    0,
    "ChangedSoname":     0,
    "TotalObjects":      3
  },
  {
    "Version":           "2.4.43",
    "From":              "2.4.42",
    "BC":                "100%",
    "Added":             0,
    "Removed":           0,
    "TotalProblems":     0,
    "ObjectsAdded":      0,
    "ObjectsRemoved":    0,
    "ChangedSoname":     0,
    "TotalObjects":      3
  },
  {
    "Version":           "2.4.42",
    "From":              "2.4.41",
    "BC":                "100%",
    "Added":             0,
    "Removed":           0,
    "TotalProblems":     0,
    "ObjectsAdded":      0,
    "ObjectsRemoved":    0,
    "ChangedSoname":     0,
    "TotalObjects":      3
  },
  {
    "Version":           "2.4.41",
    "From":              "2.4.40",
    "BC":                "100%",
    "Added":             0,
    "Removed":           0,
    "TotalProblems":     0,
    "ObjectsAdded":      0,
    "ObjectsRemoved":    0,
    "ChangedSoname":     0,
    "TotalObjects":      3
  },
  {
    "Version":           "2.4.40",
    "From":              "2.4.39",
    "BC":                "100%",
    "Added":             0,
    "Removed":           0,
    "TotalProblems":     0,
    "ObjectsAdded":      0,
    "ObjectsRemoved":    0,
    "ChangedSoname":     0,
    "TotalObjects":      3
  },
  {
    "Version":           "2.4.39",
    "From":              "2.4.38",
    "BC":                "100%",
    "Added":             0,
    "Removed":           0,
    "TotalProblems":     0,
    "ObjectsAdded":      0,
    "ObjectsRemoved":    0,
    "ChangedSoname":     0,
    "TotalObjects":      3
  },
  {
    "Version":           "2.4.38",
    "From":              "2.4.37",
    "BC":                "100%",
    "Added":             0,
    "Removed":           0,
    "TotalProblems":     0,
    "ObjectsAdded":      0,
    "ObjectsRemoved":    0,
    "ChangedSoname":     0,
    "TotalObjects":      3
  },
  {
    "Version":           "2.4.37",
    "From":              "2.4.36",
    "BC":                "100%",
    "Added":             0,
    "Removed":           0,
    "TotalProblems":     0,
    "ObjectsAdded":      0,
    "ObjectsRemoved":    0,
    "ChangedSoname":     0,
    "TotalObjects":      3
  },
  {
    "Version":           "2.4.36",
    "From":              "2.4.35",
    "BC":                "100%",
    "Added":             0,
    "Removed":           0,
    "TotalProblems":     0,
    "ObjectsAdded":      0,
    "ObjectsRemoved":    0,
    "ChangedSoname":     0,
    "TotalObjects":      3
  },
  {
    "Version":           "2.4.35",
    "From":              "2.4.34",
    "BC":                "100%",
    "Added":             0,
    "Removed":           0,
    "TotalProblems":     0,
    "ObjectsAdded":      0,
    "ObjectsRemoved":    0,
    "ChangedSoname":     0,
    "TotalObjects":      3
  },
  {
    "Version":           "2.4.34",
    "From":              "2.4.33",
    "BC":                "99.82%",
    "Added":             0,
    "Removed":           0,
    "TotalProblems":     2,
    "ObjectsAdded":      0,
    "ObjectsRemoved":    0,
    "ChangedSoname":     0,
    "TotalObjects":      3
  },
  {
    "Version":           "2.4.33",
    "From":              "2.4.32",
    "BC":                "100%",
    "Added":             0,
    "Removed":           0,
    "TotalProblems":     0,
    "ObjectsAdded":      0,
    "ObjectsRemoved":    0,
    "ChangedSoname":     0,
    "TotalObjects":      3
  },
  {
    "Version":           "2.4.32",
    "From":              "2.4.31",
    "BC":                "100%",
    "Added":             0,
    "Removed":           0,
    "TotalProblems":     0,
    "ObjectsAdded":      0,
    "ObjectsRemoved":    0,
    "ChangedSoname":     0,
    "TotalObjects":      3
  },
  {
    "Version":           "2.4.31",
    "From":              "2.4.30",
    "BC":                "100%",
    "Added":             0,
    "Removed":           0,
    "TotalProblems":     0,
    "ObjectsAdded":      0,
    "ObjectsRemoved":    0,
    "ChangedSoname":     0,
    "TotalObjects":      3
  },
  {
    "Version":           "2.4.30",
    "From":              "2.4.29",
    "BC":                "100%",
    "Added":             0,
    "Removed":           0,
    "TotalProblems":     0,
    "ObjectsAdded":      0,
    "ObjectsRemoved":    0,
    "ChangedSoname":     0,
    "TotalObjects":      3
  },
  {
    "Version":           "2.4.29",
    "From":              "2.4.28",
    "BC":                "100%",
    "Added":             0,
    "Removed":           0,
    "TotalProblems":     0,
    "ObjectsAdded":      0,
    "ObjectsRemoved":    0,
    "ChangedSoname":     0,
    "TotalObjects":      3
  },
  {
    "Version":           "2.4.28",
    "From":              "2.4.27",
    "BC":                "100%",
    "Added":             0,
    "Removed":           0,
    "TotalProblems":     0,
    "ObjectsAdded":      0,
    "ObjectsRemoved":    0,
    "ChangedSoname":     0,
    "TotalObjects":      3
  },
  {
    "Version":           "2.4.27",
    "From":              "2.4.26",
    "BC":                "100%",
    "Added":             4,
    "Removed":           0,
    "TotalProblems":     0,
    "ObjectsAdded":      0,
    "ObjectsRemoved":    0,
    "ChangedSoname":     0,
    "TotalObjects":      3
  },
  {
    "Version":           "2.4.26",
    "From":              "2.4.25",
    "BC":                "100%",
    "Added":             0,
    "Removed":           0,
    "TotalProblems":     0,
    "ObjectsAdded":      0,
    "ObjectsRemoved":    0,
    "ChangedSoname":     0,
    "TotalObjects":      3
  },
  {
    "Version":           "2.4.25",
    "From":              "2.4.24",
    "BC":                "100%",
    "Added":             0,
    "Removed":           0,
    "TotalProblems":     0,
    "ObjectsAdded":      0,
    "ObjectsRemoved":    0,
    "ChangedSoname":     0,
    "TotalObjects":      3
  }]
}
